ksxt/__init__.py
ksxt/bithumb.py
ksxt/koreainvest.py
ksxt/upbit.py
ksxt/api/__init__.py
ksxt/api/bithumb.py
ksxt/api/koreainvest.py
ksxt/api/upbit.py
ksxt/api/auto/api_generator.py
ksxt/api/auto/bithumb.py
ksxt/api/auto/koreainvest.py
ksxt/api/auto/upbit.py
ksxt/async_/__init__.py
ksxt/async_/bithumb.py
ksxt/async_/koreainvest.py
ksxt/async_/upbit.py
ksxt/async_/base/__init__.py
ksxt/async_/base/async_exchange.py
ksxt/base/__init__.py
ksxt/base/com_exchange.py
ksxt/base/errors.py
ksxt/base/exchange.py
ksxt/base/rate_limiter.py
ksxt/base/rest_exchange.py
ksxt/base/types.py
ksxt/config/__init__.py
ksxt/config/bithumb.toml
ksxt/config/koreainvest.toml
ksxt/config/token.toml
ksxt/config/upbit.toml
ksxt/market/base.py
ksxt/market/db.py
ksxt/market/logging.py
ksxt/market/manager.py
ksxt/market/markets.py
ksxt/market/krx/kosdaq.py
ksxt/market/krx/kospi.py
ksxt/market/krx/stock.py
ksxt/market/us/amex.py
ksxt/market/us/nasdaq.py
ksxt/market/us/nyse.py
ksxt/market/us/stock.py
ksxt/models/__init__.py
ksxt/models/balance.py
ksxt/models/cash.py
ksxt/models/common.py
ksxt/models/error.py
ksxt/models/historical.py
ksxt/models/market.py
ksxt/models/order.py
ksxt/models/orderbook.py
ksxt/models/ticker.py
ksxt/models/token.py
ksxt/models/transaction.py
ksxt/parser/bithumb.py
ksxt/parser/koreainvest.py
ksxt/parser/parser.py
ksxt/parser/upbit.py
ksxt/sample/symbol_sync.ipynb
ksxt/utils/safer.py
ksxt/utils/sorter.py
ksxt/utils/timer.py
ksxt-1.0.9.dist-info/LICENSE.txt
ksxt-1.0.9.dist-info/METADATA
ksxt-1.0.9.dist-info/WHEEL
ksxt-1.0.9.dist-info/top_level.txt
ksxt-1.0.9.dist-info/RECORD
