Metadata-Version: 2.1
Name: ksxt
Version: 1.0.9
License: MIT License
License-File: LICENSE.txt
Requires-Dist: requests
Requires-Dist: pandas
Requires-Dist: sqlalchemy
Requires-Dist: yarl
Requires-Dist: aiohttp
Requires-Dist: aiofiles
Requires-Dist: toml
Requires-Dist: pyjwt
Requires-Dist: pydantic
Requires-Dist: black
Requires-Dist: pytz
